persona_export/configuration/Configuration.py
persona_export/configuration/__init__.py
persona_export/exports/BaseExport.py
persona_export/exports/Connectors.py
persona_export/exports/DataPlatformExporter.py
persona_export/exports/DummyExporter.py
persona_export/exports/FacebookExporter.py
persona_export/exports/FacebookManualExporter.py
persona_export/exports/HistorizedInsightExporter.py
persona_export/exports/SalesForceMarketingCloudExporter.py
persona_export/exports/Validations.py
persona_export/exports/__init__.py
persona_export/main.py
persona_export/services/ServiceProvider.py
persona_export/services/__init__.py
persona_export/sql/BuildCharts.py
persona_export/sql/QueryBuilder.py
persona_export/sql/__init__.py
persona_export/utils/FileOps.py
persona_export/utils/__init__.py
odap_export_orchestrator-0.1.7.dist-info/LICENSE
odap_export_orchestrator-0.1.7.dist-info/WHEEL
odap_export_orchestrator-0.1.7.dist-info/METADATA
odap_export_orchestrator-0.1.7.dist-info/RECORD
