Metadata-Version: 2.1
Name: odap-export-orchestrator
Version: 0.1.7
Summary: DataSentics odap export orchestrator
Home-page: https://github.com/DataSentics/odap-export-orchestrator
License: MIT
Author: Pavla Moravkova
Author-email: pavla.moravkova@datasentics.com
Requires-Python: >=3.7.1,<4.0.0
Classifier: License :: OSI Approved :: MIT License
Classifier: Operating System :: OS Independent
Classifier: Programming Language :: Python :: 3
Classifier: Programming Language :: Python :: 3.10
Classifier: Programming Language :: Python :: 3.8
Classifier: Programming Language :: Python :: 3.9
Requires-Dist: azure.storage.blob (>=12.8.1,<13.0.0)
Requires-Dist: pandas (>=1.2.4,<2.0.0)
Requires-Dist: pydantic (>=1.8.2,<2.0.0)
Requires-Dist: tables (>=3.6.1,<4.0.0)
Project-URL: Repository, https://github.com/DataSentics/odap-export-orchestrator
